<?xml version="1.0" encoding="utf-8"?>
<Defs>


	<!-- Spirits -->

		<!-- Wind Spirit -->

			<HediffDef ParentName="DiseaseBase">
				<defName>Isekai_Hediff_Spirit_Wind</defName>
				<label>Wind Spirit</label>
				<description>Blessed by a wind spirit. Greater forms may give more advantages.</description>
				<defaultLabelColor>(0.0, 0.8, 0.0)</defaultLabelColor>
				<isBad>false</isBad>
				<everCurableByItem>false</everCurableByItem>
				<initialSeverity>1</initialSeverity>
				<maxSeverity>3</maxSeverity>
				<stages>
					<li>
						<label>lesser</label>
						<statOffsets>
							<ArmorRating_Magic>0.1</ArmorRating_Magic>
							<ArmorRating_Elemental>0.2</ArmorRating_Elemental>
							<MoveSpeed>0.2</MoveSpeed>
							<CrawlSpeed>0.04</CrawlSpeed>
							<CaravanRidingSpeedFactor>0.1</CaravanRidingSpeedFactor>
							<ToxicResistance>0.2</ToxicResistance>
							<ToxicEnvironmentResistance MayRequire="Ludeon.RimWorld.Biotech">0.2</ToxicEnvironmentResistance>
						</statOffsets>
					</li>
					<li>
						<minSeverity>2</minSeverity>
						<label>medium</label>
						<statOffsets>
							<ArmorRating_Magic>0.3</ArmorRating_Magic>
							<ArmorRating_Elemental>0.5</ArmorRating_Elemental>
							<MoveSpeed>0.5</MoveSpeed>
							<CrawlSpeed>0.07</CrawlSpeed>
							<CaravanRidingSpeedFactor>0.2</CaravanRidingSpeedFactor>
							<ToxicResistance>0.5</ToxicResistance>
							<ToxicEnvironmentResistance MayRequire="Ludeon.RimWorld.Biotech">0.5</ToxicEnvironmentResistance>
						</statOffsets>
					</li>
					<li>
						<minSeverity>3</minSeverity>
						<label>greater</label>
						<statOffsets>
							<ArmorRating_Magic>0.5</ArmorRating_Magic>
							<ArmorRating_Elemental>1.0</ArmorRating_Elemental>
							<MoveSpeed>1.0</MoveSpeed>
							<CrawlSpeed>0.1</CrawlSpeed>
							<CaravanRidingSpeedFactor>0.5</CaravanRidingSpeedFactor>
							<ToxicResistance>1</ToxicResistance>
							<ToxicEnvironmentResistance MayRequire="Ludeon.RimWorld.Biotech">1</ToxicEnvironmentResistance>
						</statOffsets>
					</li>
				</stages>
				<comps>
				</comps>
			</HediffDef>

		<!-- Fire Spirit -->

			<HediffDef ParentName="DiseaseBase">
				<defName>Isekai_Hediff_Spirit_Fire</defName>
				<label>Fire Spirit</label>
				<description>Blessed by a fire spirit. Greater forms may give more advantages.</description>
				<defaultLabelColor>(0.8, 0.0, 0.0)</defaultLabelColor>
				<isBad>false</isBad>
				<everCurableByItem>false</everCurableByItem>
				<initialSeverity>1</initialSeverity>
				<maxSeverity>3</maxSeverity>
				<stages>
					<li>
						<label>lesser</label>
						<statOffsets>
							<ArmorRating_Magic>0.1</ArmorRating_Magic>
							<ArmorRating_Elemental>0.2</ArmorRating_Elemental>
							<ArmorRating_Heat>0.2</ArmorRating_Heat>
						</statOffsets>
						<statFactors>
    						<Flammability>0</Flammability>
						</statFactors>
						<damageFactors>
							<Flame>0.8</Flame>
							<Burn>0.8</Burn>
						</damageFactors>
					</li>
					<li>
						<minSeverity>2</minSeverity>
						<label>medium</label>
						<statOffsets>
							<ArmorRating_Magic>0.3</ArmorRating_Magic>
							<ArmorRating_Elemental>0.5</ArmorRating_Elemental>
							<ArmorRating_Heat>0.5</ArmorRating_Heat>
						</statOffsets>
						<statFactors>
    						<Flammability>0</Flammability>
						</statFactors>
						<damageFactors>
							<Flame>0.5</Flame>
							<Burn>0.5</Burn>
						</damageFactors>
					</li>
					<li>
						<minSeverity>3</minSeverity>
						<label>greater</label>
						<statOffsets>
							<ArmorRating_Magic>0.5</ArmorRating_Magic>
							<ArmorRating_Elemental>1.0</ArmorRating_Elemental>
							<ArmorRating_Heat>1.0</ArmorRating_Heat>
						</statOffsets>
						<statFactors>
    						<Flammability>0</Flammability>
						</statFactors>
						<damageFactors>
							<Flame>0</Flame>
							<Burn>0</Burn>
						</damageFactors>
					</li>
				</stages>
				<comps>
				</comps>
			</HediffDef>

		<!-- Water Spirit -->

			<HediffDef ParentName="DiseaseBase">
				<defName>Isekai_Hediff_Spirit_Water</defName>
				<label>Water Spirit</label>
				<description>Blessed by a water spirit. Greater forms may give more advantages.</description>
				<defaultLabelColor>(0.0, 0.4, 0.8)</defaultLabelColor>
				<isBad>false</isBad>
				<everCurableByItem>false</everCurableByItem>
				<initialSeverity>1</initialSeverity>
				<maxSeverity>3</maxSeverity>
				<stages>
					<li>
						<label>lesser</label>
						<statOffsets>
							<ArmorRating_Magic>0.1</ArmorRating_Magic>
							<ArmorRating_Elemental>0.2</ArmorRating_Elemental>
						</statOffsets>
					</li>
					<li>
						<minSeverity>2</minSeverity>
						<label>medium</label>
						<statOffsets>
							<ArmorRating_Magic>0.3</ArmorRating_Magic>
							<ArmorRating_Elemental>0.5</ArmorRating_Elemental>
						</statOffsets>
					</li>
					<li>
						<minSeverity>3</minSeverity>
						<label>greater</label>
						<statOffsets>
							<ArmorRating_Magic>0.5</ArmorRating_Magic>
							<ArmorRating_Elemental>1.0</ArmorRating_Elemental>
						</statOffsets>
					</li>
				</stages>
				<comps>
					<li Class="AnimalBehaviours.HediffCompProperties_Waterstriding"/>
				</comps>
			</HediffDef>

		<!-- Earth Spirit -->

			<HediffDef ParentName="DiseaseBase">
				<defName>Isekai_Hediff_Spirit_Earth</defName>
				<label>Earth Spirit</label>
				<description>Blessed by an earth spirit. Greater forms may give more advantages.</description>
				<defaultLabelColor>(0.8, 0.4, 0.0)</defaultLabelColor>
				<isBad>false</isBad>
				<everCurableByItem>false</everCurableByItem>
				<initialSeverity>1</initialSeverity>
				<maxSeverity>3</maxSeverity>
				<stages>
					<li>
						<label>lesser</label>
						<statOffsets>
							<ArmorRating_Magic>0.1</ArmorRating_Magic>
							<ArmorRating_Elemental>0.2</ArmorRating_Elemental>
						</statOffsets>
					</li>
					<li>
						<minSeverity>2</minSeverity>
						<label>medium</label>
						<statOffsets>
							<ArmorRating_Magic>0.3</ArmorRating_Magic>
							<ArmorRating_Elemental>0.5</ArmorRating_Elemental>
						</statOffsets>
					</li>
					<li>
						<minSeverity>3</minSeverity>
						<label>greater</label>
						<statOffsets>
							<ArmorRating_Magic>0.5</ArmorRating_Magic>
							<ArmorRating_Elemental>1.0</ArmorRating_Elemental>
						</statOffsets>
					</li>
				</stages>
				<comps>
				</comps>
			</HediffDef>

		<!-- Light / Holy Spirit -->

			<HediffDef ParentName="DiseaseBase">
				<defName>Isekai_Hediff_Spirit_Light</defName>
				<label>Light Spirit</label>
				<description>Blessed by a light spirit, also known as holy spirit. Greater forms may give more advantages.</description>
				<defaultLabelColor>(0.9, 0.9, 0.0)</defaultLabelColor>
				<isBad>false</isBad>
				<everCurableByItem>false</everCurableByItem>
				<initialSeverity>1</initialSeverity>
				<maxSeverity>3</maxSeverity>
				<stages>
					<li>
						<label>lesser</label>
						<statOffsets>
							<ArmorRating_Magic>0.1</ArmorRating_Magic>
							<ArmorRating_Holy>0.2</ArmorRating_Holy>
						</statOffsets>
					</li>
					<li>
						<minSeverity>2</minSeverity>
						<label>medium</label>
						<statOffsets>
							<ArmorRating_Magic>0.3</ArmorRating_Magic>
							<ArmorRating_Holy>0.5</ArmorRating_Holy>
						</statOffsets>
					</li>
					<li>
						<minSeverity>3</minSeverity>
						<label>greater</label>
						<statOffsets>
							<ArmorRating_Magic>0.5</ArmorRating_Magic>
							<ArmorRating_Holy>1.0</ArmorRating_Holy>
						</statOffsets>
					</li>
				</stages>
				<comps>
				</comps>
			</HediffDef>





</Defs>
