<?xml version="1.0" encoding="utf-8"?>
<Defs>


		<HediffDef Name="Isekai_InjuryBase" ParentName="InjuryBase">
			<defName>Isekai_Cut_Small</defName>
			<label>Cut</label>
			<labelNoun>A small cut.</labelNoun>
			<description>A small cut.</description>
			<comps>
				<li Class="HediffCompProperties_TendDuration">
					<labelTendedWell>treated</labelTendedWell>
					<labelTendedWellInner>stabilized</labelTendedWellInner>
					<labelSolidTendedWell>set</labelSolidTendedWell>
				</li>
				<li Class="HediffCompProperties_Infecter">
					<infectionChance>0.15</infectionChance>
				</li>
				<li Class="HediffCompProperties_GetsPermanent">
					<permanentLabel>cut scar</permanentLabel>
				</li>
			</comps>
			<injuryProps>
				<painPerSeverity>0.005</painPerSeverity>
				<averagePainPerSeverityPermanent>0.00325</averagePainPerSeverityPermanent>
				<bleedRate>0.02</bleedRate>
				<canMerge>false</canMerge>
				<destroyedLabel>Cut off</destroyedLabel>
				<destroyedOutLabel>Cut out</destroyedOutLabel>
			</injuryProps>
		</HediffDef>

		<HediffDef ParentName="Isekai_InjuryBase">
			<defName>Isekai_Injury_Magic</defName>
			<label>Magic Injury</label>
			<labelNoun>A magic injury.</labelNoun>
			<description>A magic injury.</description>
			<injuryProps>
				<painPerSeverity>0.01</painPerSeverity>
				<averagePainPerSeverityPermanent>0.0065</averagePainPerSeverityPermanent>
				<bleedRate>0.04</bleedRate>
				<destroyedLabel>Cut off</destroyedLabel>
				<destroyedOutLabel>Cut out</destroyedOutLabel>
			</injuryProps>
		</HediffDef>









</Defs>
